Workbook

Sheet 30 Questions
A1: Q# | B1: Domain | C1: Domain name | D1: Question text | E1: Phr | F1: Sec | G1: CT / Era | H1: Control type (K only) | I1: Expected answer | J1: Key authority (outdated → current) / Why it is a trap (K controls) | K1: Source URL(s) | L1: Conf
A2: Q1 | B2: A | C2: A. Arrest and custody rights (3) | D2: "Police picked up my brother last night from Andheri after his car hit a scooter, they just said 'come with us' and took his phone, no paper nothing, my mother is crying since morning. Today they took him to magistrate for remand. The lawyer says it's fine but I read online they must give reasons?? Is this arrest even legal, can we get him out because they gave nothing in writing?" | E2: N | F2: NONE | G2: CT: Y / Era: Y | H2: — | I2: Grounds of arrest must be given in writing, in a language the arrestee understands, for every offence (IPC/BNS included), and at least 2 hours before production for remand. If not, the arrest and remand are illegal and he is entitled to release. Some High Courts apply this only to arrests made after 6 Nov 2025. | J2: Outdated: Pankaj Bansal (2023) and Prabir Purkayastha (2024) required written grounds only under PMLA/UAPA, and Vihaan Kumar (2025) treated writing as ideal rather than mandatory. Current: Mihir Rajesh Shah v. State of Maharashtra, SC, 6 Nov 2025, 2025 INSC 1288 (Gavai CJI, Masih J). A Delhi HC Division Bench in Karan Singh v. State (NCT of Delhi), 2026:DHC:570-DB (reported 28 Jan 2026), held the written-grounds mandate "operates prospectively", but a later Delhi HC NDPS ruling rejected the prospective-only argument, so the Delhi HC is itself split. | K2: https://indiankanoon.org/doc/75521991/ https://www.livelaw.in/pdf_upload/2025-livelaw-sc-1066-mihir-rajesh-shah-v-state-of-maharashtra-6-nov-2025-632170.pdf https://www.livelaw.in/high-court/delhi-high-court/delhi-high-court-supreme-court-mihir-rajesh-shah-ruling-written-grounds-arrest-prospectively-520838 | L2: [L]
A3: Q2 | B3: A | C3: A. Arrest and custody rights (3) | D3: "Police sent me a notice on WhatsApp under section 35 BNSS to come to the station tomorrow in a cheating case. Is a WhatsApp notice valid? Can they arrest me if I don't go?" | E3: E | F3: NEW | G3: CT: N / Era: Y | H3: — | I3: No. A s.35 BNSS (old s.41A CrPC) notice must be served in a mode the statute prescribes; WhatsApp or email service is invalid. For offences punishable up to 7 years, a notice is the rule and arrest the exception. Arrest for non-compliance needs a validly served notice and recorded reasons. | J3: Satender Kumar Antil v. CBI, SC, 2025 INSC 909 (Sundresh & Kotiswar Singh JJ), upholding the 21 Jan 2025 order. Satender Kumar Antil v. CBI (2022) 10 SCC 51. Arnesh Kumar v. State of Bihar (2014) 8 SCC 273. BNSS s.35 = CrPC s.41A. | K3: https://www.verdictum.in/court-updates/supreme-court/satender-kumar-antil-v-central-bureau-of-investigation-2025-insc-909-electronic-communication-service-of-notice-section-35-bnss-whatsapp-1586826 https://www.livelaw.in/high-court/karnataka-high-court/karnataka-high-court-appearance-notice-served-physically-whatsapp-email-section35-bnss-528956 | L3: [C]
A4: Q3 | B4: A | C4: A. Arrest and custody rights (3) | D4: "What are the mandatory obligations of the arresting officer under Sections 41B, 41D and 50A CrPC, and what are the consequences of non-compliance in light of the D.K. Basu requirements?" | E4: L | F4: OLD | G4: CT: N / Era: N | H4: — | I4: The officer must prepare an arrest memo attested by a witness and countersigned by the arrestee, inform a relative or friend, and let the arrestee meet an advocate during (not throughout) interrogation. Breach exposes officers to departmental action and contempt, and the State to public-law compensation. The BNSS equivalents are ss.36, 38 and 48. | J4: D.K. Basu v. State of West Bengal (1997) 1 SCC 416. CrPC ss.41B/41D/50A = BNSS ss.36/38/48. | K4: indiankanoon.org (search "D.K. Basu v. State of West Bengal"; URL not retrieved this pass) | L4: [C]
A5: Q4 | B5: B | C5: B. Bail: regular, anticipatory, default (3) | D5: "Whether an order of anticipatory bail under Section 438 CrPC must necessarily be limited in time or until the filing of the charge-sheet, or whether it may continue till the end of trial." | E5: L | F5: OLD | G5: CT: Y / Era: Y | H5: — | I5: No fixed time limit is needed. Protection ordinarily lasts until the end of trial unless the court restricts it for case-specific reasons. Section 438 CrPC is now s.482 BNSS. | J5: Outdated: Salauddin Abdulsamad Shaikh v. State of Maharashtra (1996) 1 SCC 667 (time-limited protection). Current: Sushila Aggarwal v. State (NCT of Delhi), SC Constitution Bench, 29 Jan 2020, (2020) 5 SCC 1, 2020 INSC 106. | K5: https://indiankanoon.org/search/?formInput=cites%3A79537784 | L5: [C]
A6: Q5 | B6: B | C6: B. Bail: regular, anticipatory, default (3) | D6: "my father is in jail since 88 days in a CBI bank fraud case. CBI filed chargesheet on day 87 but says investigation against 'other accused' is still going on and they didn't even give us copy of chargesheet yet. Our lawyer is saying we can get default bail under section 187 BNSS because chargesheet is incomplete, citing some Ritu Chhabaria case. Someone else told me that case was stopped by Supreme Court. Please tell what is the actual position, we are very confused." | E6: N | F6: NEW | G6: CT: Y / Era: Y | H6: — | I6: Probably not. Default bail under s.187(3) BNSS (old s.167(2) CrPC) is lost once a charge-sheet in proper form is filed within 60/90 days. Pending further investigation against other accused does not revive it, and neither does failure to supply copies. Ritu Chhabaria's "incomplete charge-sheet" reasoning was put on hold in 2023; the CBI's review was dismissed in Aug 2025, but its practical reach is narrow. | J6: Outdated or contested: Ritu Chhabaria v. Union of India (SC, 26 Apr 2023), deferred by order of 1 May 2023 and clarified 12 May 2023. Current: CBI v. Kapil Wadhawan, 24 Jan 2024, (2024) 3 SCC 734, 2024 INSC 58. Shaurya Sunil Kumar Singh v. CBI, 1 Jul 2026, 2026 INSC 666 (non-supply of copies under s.193(8) BNSS is no ground). | K6: https://www.livelaw.in/top-stories/supreme-court-dismisses-cbis-review-petition-against-ritu-chhabaria-judgment-that-incomplete-chargesheet-wont-defeat-default-bail-300281 https://www.scconline.com/blog/post/2024/01/31/dhfl-fraud-case-accused-cannot-claim-statutory-right-default-bail-investigation-qua-other-accused-was-pending/ https://www.livelaw.in/supreme-court/s-1873-bnss-non-supply-of-charge-sheet-to-accused-not-ground-for-default-bail-supreme-court-539456 | L6: [L]
A7: Q6 | B7: B | C7: B. Bail: regular, anticipatory, default (3) | D7: "My nephew is first time accused in a 2023 theft case, he's been in jail as undertrial for over a year. Does the new section 479 BNSS one-third rule help him even though the FIR was before the new law?" | E7: E | F7: NEW | G7: CT: N / Era: Y | H7: — | I7: Yes. A first-time offender who has served one-third of the maximum sentence as an undertrial must be released on bond under s.479 BNSS; for theft (IPC 379, up to 3 years) that is 12 months. The Supreme Court held s.479 applies to undertrials whose cases were registered before 1 July 2024. It does not apply to offences punishable with death or life imprisonment. | J7: In Re: Inhuman Conditions in 1382 Prisons, W.P.(C) 406/2013, SC order of 23 Aug 2024 (Hima Kohli & Sandeep Mehta JJ), 2024 LiveLaw (SC) 632. BNSS s.479 replaces CrPC s.436A (one-half rule). | K7: https://api.sci.gov.in/supremecourt/2013/18545/18545_2013_9_2_55018_Order_23-Aug-2024.pdf | L7: [C]
A8: Q7 | B8: C | C8: C. Cheque bounce (NI Act s.138) (3) | D8: "I gave my old friend 6 lakhs cash for his shop, he gave cheque, it bounced, case going on in Margao court for four years now. Now suddenly he is ready to pay the cheque amount but my lawyer says he will have to pay 10% or 15% extra to settle as per some 2010 Supreme Court rules. His evidence is not recorded yet. How much extra does he actually have to pay, and can court close it even if I want to punish him?" | E8: N | F8: NONE | G8: CT: Y / Era: Y | H8: — | I8: Under the 2025 guidelines, payment before defence evidence allows compounding with no cost. After defence evidence but before judgment the cost is 5%; in appeal or revision before the Sessions Court or High Court it is 7.5%; before the Supreme Court it is 10%. The court may suggest compounding. If the complainant resists, it can consider probation-type relief. | J8: Outdated: Damodar S. Prabhu v. Sayed Babalal H. (2010) 5 SCC 663 (10/15/20% costs). Current: Sanjabij Tari v. Kishore S. Borcar, SC, 25 Sep 2025, 2025 INSC 1158 (Manmohan & N.V. Anjaria JJ). | K8: https://www.verdictum.in/court-updates/supreme-court/sanjabij-tari-v-kishore-sborcar-2025-insc-1158-summons-accused-payment-cheque-amount-initial-stage-sec138-ni-act-1592654 https://www.verdictum.in/bombay-high-court/cambium-boitech-private-ltd-v-the-state-of-maharashtra-913-crwp-4815-2025-1616479 | L8: [C]
A9: Q8 | B9: C | C9: C. Cheque bounce (NI Act s.138) (3) | D9: "In my cheque bounce case the magistrate ordered me to pay 20% interim compensation on the very first date. Is that compulsory?" | E9: E | F9: NONE | G9: CT: N / Era: Y | H9: — | I9: No. Interim compensation under s.143A(1) NI Act is discretionary. The court must first find a prima facie case, weigh how plausible the defence is and the accused's financial position, and record brief reasons. The cap is 20%. | J9: Rakesh Ranjan Shrivastava v. State of Jharkhand, SC, 15 Mar 2024, 2024 INSC 205. | K9: https://www.verdictum.in/court-updates/high-courts/rakesh-ranjan-shrivastava-v-state-of-jharkhand-2024-insc-205-section-143a-negotiable-instruments-act-discretionary-not-mandatory-1525808 | L9: [C]
A10: Q9 | B10: C | C10: C. Cheque bounce (NI Act s.138) (3) | D10: "Where the payee presents a dishonoured cheque through his account at the branch of his bank in Delhi, though the cheque is drawn on a Kolkata bank, which court has territorial jurisdiction to try the complaint?" | E10: L | F10: NONE | G10: CT: Y / Era: N | H10: — | I10: The Delhi court has jurisdiction. Under s.142(2)(a) NI Act, as amended in 2015, a cheque delivered for collection through an account is triable where the payee's branch is located. | J10: Outdated: Dashrath Rupsingh Rathod v. State of Maharashtra (2014) 9 SCC 129 (drawee bank's location only). Current: Negotiable Instruments (Amendment) Act, 2015; Bridgestone India Pvt Ltd v. Inderpal Singh, SC, 24 Nov 2015, (2016) 2 SCC 75. | K10: https://lextechsuite.com/Ms-Bridgestone-India-Pvt-Ltd-Versus-Inderpal-Singh-2015-11-24 (non-preferred portal; verify on indiankanoon) | L10: [C]
A11: Q10 | B11: D | C11: D. NDPS (2) | D11: "Whether a prosecution under the NDPS Act stands vitiated merely because the informant/complainant police officer also conducted the investigation." | E11: L | F11: NONE | G11: CT: Y / Era: Y | H11: — | I11: No automatic vitiation. Bias must be decided on the facts of each case. Mohan Lal was overruled, and the protection it gave survives only for cases already decided under it. | J11: Outdated: Mohan Lal v. State of Punjab, 16 Aug 2018, (2018) 17 SCC 627. Current: Mukesh Singh v. State (Narcotic Branch of Delhi), Constitution Bench, 31 Aug 2020, (2020) 10 SCC 120, 2020 INSC 524. | K11: https://api.sci.gov.in/supremecourt/2018/39528/39528_2018_33_1502_23731_Judgement_31-Aug-2020.pdf https://narcoticsindia.nic.in/Judgments/Mohan_Lal_vs_The_State_Of_Punjab_on_16_August_2018.pdf | L11: [C]
A12: Q11 | B12: D | C12: D. NDPS (2) | D12: "NCB made my cousin sign a statement in their office saying the ganja was his. Can they use that as his confession in court?" | E12: E | F12: NONE | G12: CT: Y / Era: Y | H12: — | I12: No. NCB officers investigating under the NDPS Act are "police officers" for s.25 of the Evidence Act (now s.23 BSA). A statement recorded under s.67 NDPS is inadmissible as a confession. | J12: Outdated: Kanhaiyalal v. Union of India (2008) 4 SCC 668 and Raj Kumar Karwal (1990), which treated these as admissible. Current: Tofan Singh v. State of Tamil Nadu, SC (2:1), (2021) 4 SCC 1, 2020 INSC 620. | K12: https://delhihighcourt.nic.in/app/showFileJudgment/NBK04112025BA38012025_155725.txt (HC applying Tofan Singh) | L12: [C]
... A31: Q30 | B31: K | C31: K. Controls / trap questions (3) | D31: "Police registered FIR in Aug 2024 under 420 and 406 IPC for a fraud done in March 2024. What are the new BNS sections for these and what is the punishment?" | E31: E | F31: OLD | G31: — | H31: K3: statute / comparison table | I31: Correct output: answer from the statute or mapping table, not a judgment. IPC 420 → BNS 318(4), up to 7 years plus fine. IPC 406 → BNS 316(2), which provides imprisonment "which may extend to five years, or with fine, or with both", up from 3 years under the IPC (confirmed by AZB & Partners' BNS overview; India Code not opened). Because the offence predates 1 July 2024, the IPC applies, though the investigation, registered after 1 July 2024, follows the BNSS. | J31: BNS 2023 text (India Code); MHA/BPR&D IPC–BNS correspondence tables. No judgment needed. | K31: https://blog.ipleaders.in/section-420-bns-cheating-318/ (secondary); verify on indiacode.nic.in | L31: [L]

Sheet Legend & Notes
A1: Indian Criminal Law Retrieval Test Set: 30 Verified Questions (as of October 2026)
A3: Summary | B3: The 30 questions below meet every distribution and mix rule. Each is tied to a Supreme Court judgment, statute or government source that was checked during this research pass. Thirteen of them are currency traps, where the ruling a search is most likely to surface has since been overruled, diluted or superseded.
A5: Legend (column codes in the '30 Questions' sheet)
A6: Phr | B6: Phrasing: E = everyday, L = legal-wording, N = long-narrative.
A7: Sec | B7: Section-number tag: NEW = BNS/BNSS/BSA, OLD = IPC/CrPC/Evidence Act, NONE = no section number.
A8: CT / Era | B8: CT = currency trap (Y/N: the ruling a search is most likely to surface was later overruled, diluted or superseded). Era = best/current law from 2017 or later (Y/N). Shown as in the report, e.g. 'CT: Y / Era: Y'. Not applicable (—) for the K controls.
A9: Control type | B9: Only for domain K: K1 = civil, tax or divorce question; K2 = point settled only by a High Court or a 2026 ruling; K3 = answered by a statute or comparison table, not a judgment.
A10: Conf | B10: Confidence that the expected answer is correct and current as of October 2026: [C] Certain, [L] Likely, [G] Guessing.
A11: Domain | B11: A–J are the ten criminal-law domains; K holds the three controls. Domain names follow the report's section headings.
A12: Source URL(s) | B12: Multiple URLs in one cell are separated by line breaks (the report separated them with ' ; '). Entries that are not URLs, such as 'indiankanoon.org (search ...)', are kept exactly as in the report.
A13: Column merge | B13: In the report, the K tables label their fifth column 'Control type' and their seventh 'Why it is a trap / correct authority'. Here the control type has its own column, and the 'why it is a trap' text sits in the authority column (J).
A15: TL;DR
A16: 1 | B16: The set has 30 questions: A–J follow the exact domain counts and K holds 3 controls. Phrasing splits into 10 everyday, 11 legal-wording and 9 long-narrative questions. By section number, 9 cite BNS/BNSS/BSA, 7 cite IPC/CrPC and 14 cite none. There are 13 currency traps, and 24 of the 27 substantive questions turn on law from 2017 or later.
A17: 2 | B17: The hardest tests are the currency traps. Examples: Mohan Lal (2018) → Mukesh Singh (2020); Damodar S. Prabhu (2010) → Sanjabij Tari (2025 INSC 1158); Shafhi Mohammad (2018) → Arjun Panditrao Khotkar (2020); Rajesh Sharma (2017) → Social Action Forum (2018) → Shivangi Bansal (2025 INSC 883). Two more involve 2026-only rulings that a Supreme Court index with an earlier cutoff will not contain: State of A.P. v. Suda Suresh Veera Venkata Naga Raju (2026 INSC 744) and Shaurya Sunil Kumar Singh v. CBI (2026 INSC 666).
A18: 3 | B18: Seven expected answers turn on unsettled or fast-moving law and should be checked by a practising advocate before scoring: Shivangi Bansal versus Social Action Forum, the status of Ritu Chhabaria, whether Mihir Rajesh Shah applies prospectively, the pending review of Vijay Madanlal, BNS 69 versus IPC 376, the BNS 316(2) punishment, and several SCC citations that could only be confirmed secondhand.
A20: Key Findings
A21: 1 | B21: IPC/BNS transition rule (applies throughout): The offence date decides the substantive law. Conduct on or before 30 June 2024 is tried under the IPC; conduct from 1 July 2024 falls under the BNS. Under the BNSS saving clause (s.531(2)(a)), investigations, inquiries, trials and appeals already pending on 1 July 2024 continue under the CrPC. The Supreme Court has nonetheless applied some beneficial BNSS provisions, such as s.479, to undertrials whose cases began earlier (Q6).
A22: 2 | B22: Currency risk is concentrated in procedure. Grounds of arrest, default bail, compounding, remission and the 498A safeguards all shifted between 2023 and 2026. A tool trained on older headnotes will tend to give confident but outdated answers.
A23: 3 | B23: Citation hygiene: Neutral citations were confirmed for most post-2019 rulings. Where only an SCC cite, or only a secondary source, was available, the table says so.
A25: Caveats
A26: 1 | B26: Several 2025–2026 rulings were confirmed through LiveLaw, Verdictum or SCC Online reports rather than the full judgment text. Neutral citations come from those reports.
A27: 2 | B27: Q29 (K2) is a Supreme Court ruling, but it qualifies as a control because it is 2026-only. If the index cutoff falls after July 2026, swap in a ruling from after the cutoff.
A28: 3 | B28: In Q6 the release is not automatic: under the second proviso to s.479 BNSS, the court keeps discretion to order continued detention.

Sheet Compliance Check
A1: Rule | B1: Required | C1: Actual (as in report) | D1: Questions | E1: Result (as in report) | F1: Live count (formula) | G1: Live result (formula)
A2: A Arrest/custody | B2: 3 | C2: 3 | D2: Q1–Q3 | E2: PASS | F2: =COUNTIF('30 Questions'!$B$2:$B$31,"A") -> 3 | G2: =IF(F2=B2,"PASS","FAIL") -> PASS
A3: B Bail | B3: 3 | C3: 3 | D3: Q4–Q6 | E3: PASS | F3: =COUNTIF('30 Questions'!$B$2:$B$31,"B") -> 3 | G3: =IF(F3=B3,"PASS","FAIL") -> PASS
A4: C Cheque bounce | B4: 3 | C4: 3 | D4: Q7–Q9 | E4: PASS | F4: =COUNTIF('30 Questions'!$B$2:$B$31,"C") -> 3 | G4: =IF(F4=B4,"PASS","FAIL") -> PASS
A5: D NDPS | B5: 2 | C5: 2 | D5: Q10–Q11 | E5: PASS | F5: =COUNTIF('30 Questions'!$B$2:$B$31,"D") -> 2 | G5: =IF(F5=B5,"PASS","FAIL") -> PASS
A6: E FIR quashing | B6: 3 | C6: 3 | D6: Q12–Q14 | E6: PASS | F6: =COUNTIF('30 Questions'!$B$2:$B$31,"E") -> 3 | G6: =IF(F6=B6,"PASS","FAIL") -> PASS
A7: F Marriage-related | B7: 3 | C7: 3 | D7: Q15–Q17 | E7: PASS | F7: =COUNTIF('30 Questions'!$B$2:$B$31,"F") -> 3 | G7: =IF(F7=B7,"PASS","FAIL") -> PASS
A8: G Sexual offences/POCSO | B8: 3 | C8: 3 | D8: Q18–Q20 | E8: PASS | F8: =COUNTIF('30 Questions'!$B$2:$B$31,"G") -> 3 | G8: =IF(F8=B8,"PASS","FAIL") -> PASS
A9: H Violent crime | B9: 3 | C9: 3 | D9: Q21–Q23 | E9: PASS | F9: =COUNTIF('30 Questions'!$B$2:$B$31,"H") -> 3 | G9: =IF(F9=B9,"PASS","FAIL") -> PASS
A10: I PMLA/UAPA/SC-ST/corruption | B10: 2 | C10: 2 | D10: Q24–Q25 | E10: PASS | F10: =COUNTIF('30 Questions'!$B$2:$B$31,"I") -> 2 | G10: =IF(F10=B10,"PASS","FAIL") -> PASS
A11: J After conviction | B11: 2 | C11: 2 | D11: Q26–Q27 | E11: PASS | F11: =COUNTIF('30 Questions'!$B$2:$B$31,"J") -> 2 | G11: =IF(F11=B11,"PASS","FAIL") -> PASS
A12: K Controls | B12: 3 | C12: 3 | D12: Q28–Q30 | E12: PASS | F12: =COUNTIF('30 Questions'!$B$2:$B$31,"K") -> 3 | G12: =IF(F12=B12,"PASS","FAIL") -> PASS
A13: Total | B13: 30 | C13: 30 | D13: — | E13: PASS | F13: =COUNTA('30 Questions'!$A$2:$A$31) -> 30 | G13: =IF(F13=B13,"PASS","FAIL") -> PASS
A14: Everyday phrasing | B14: ≥5 | C14: 10 | D14: Q2, Q6, Q8, Q11, Q14, Q16, Q18, Q23, Q28, Q30 | E14: PASS | F14: =COUNTIF('30 Questions'!$E$2:$E$31,"E") -> 10 | G14: =IF(F14>=5,"PASS","FAIL") -> PASS
A15: Legal-wording phrasing | B15: ≥5 | C15: 11 | D15: Q3, Q4, Q9, Q10, Q13, Q17, Q20, Q21, Q25, Q26, Q29 | E15: PASS | F15: =COUNTIF('30 Questions'!$E$2:$E$31,"L") -> 11 | G15: =IF(F15>=5,"PASS","FAIL") -> PASS
A16: Long-narrative phrasing | B16: ≥5 | C16: 9 | D16: Q1, Q5, Q7, Q12, Q15, Q19, Q22, Q24, Q27 | E16: PASS | F16: =COUNTIF('30 Questions'!$E$2:$E$31,"N") -> 9 | G16: =IF(F16>=5,"PASS","FAIL") -> PASS
A17: New-code numbers (BNS/BNSS/BSA) | B17: ≥5 | C17: 9 | D17: Q2, Q5, Q6, Q13, Q15, Q20, Q21, Q26, Q29 | E17: PASS | F17: =COUNTIF('30 Questions'!$F$2:$F$31,"NEW") -> 9 | G17: =IF(F17>=5,"PASS","FAIL") -> PASS
A18: Old-code numbers (IPC/CrPC/Evidence) | B18: ≥5 | C18: 7 | D18: Q3, Q4, Q12, Q17, Q22, Q25, Q30 | E18: PASS | F18: =COUNTIF('30 Questions'!$F$2:$F$31,"OLD") -> 7 | G18: =IF(F18>=5,"PASS","FAIL") -> PASS
A19: No section number | B19: rest | C19: 14 | D19: Q1, Q7–Q11, Q14, Q16, Q18, Q19, Q23, Q24, Q27, Q28 | E19: PASS | F19: =COUNTIF('30 Questions'!$F$2:$F$31,"NONE") -> 14 | G19: =IF(F19=COUNTA('30 Questions'!$A$2:$A$31)-F17-F18,"PASS","FAIL") -> PASS
A20: Controls by type (K1/K2/K3) | B20: 1 each | C20: 1/1/1 | D20: Q28 / Q29 / Q30 | E20: PASS | F20: =COUNTIF('30 Questions'!$H$2:$H$31,"K1*")&"/"&COUNTIF('30 Questions'!$H$2:$H$31,"K2*")&"/"&COUNTIF('30 Questions'!$H$2:$H$31,"K3*") -> 1/1/1 | G20: =IF(F20="1/1/1","PASS","FAIL") -> PASS
A21: Currency traps (A–J) | B21: ≥3 | C21: 13 | D21: Q1, Q4, Q5, Q7, Q9, Q10, Q11, Q15, Q18, Q21, Q24, Q25, Q27 | E21: PASS | F21: =COUNTIF('30 Questions'!$G$2:$G$31,"CT: Y*") -> 13 | G21: =IF(F21>=3,"PASS","FAIL") -> PASS
A22: Era 2017+ (A–J) | B22: ≥8 | C22: 24 | D22: All A–J except Q3, Q9, Q23 | E22: PASS | F22: =COUNTIF('30 Questions'!$G$2:$G$31,"*Era: Y") -> 24 | G22: =IF(F22>=8,"PASS","FAIL") -> PASS
A24: Notes
A25: Columns A–E reproduce the report's compliance table exactly. Columns F–G are live formulas that recount the '30 Questions' sheet, so the check re-evaluates if a question is edited.
A26: Rule thresholds used in column G (taken from the brief): domain counts are exact; each phrasing style and each of NEW/OLD section tags needs at least 5; currency traps at least 3; era 2017+ at least 8; controls exactly one each of K1/K2/K3; 'No section number' must equal 30 minus the NEW and OLD counts.
A27: Currency-trap and era counts use the 'CT / Era' text (e.g. 'CT: Y / Era: Y'); the K controls carry '—' there, so both counts cover domains A–J only.

Sheet Currency Traps
A1: Q# | B1: Outdated ruling (likely first hit) | C1: Current authority | D1: What changed
A2: Q1 | B2: Pankaj Bansal (2023) / Prabir Purkayastha (2024): written grounds required under PMLA/UAPA only | C2: Mihir Rajesh Shah, 2025 INSC 1288 | D2: Written grounds now required for every offence, at least 2 hours before remand; prospective application disputed
A3: Q4 | B3: Salauddin Abdulsamad Shaikh (1996) | C3: Sushila Aggarwal (2020) 5 SCC 1 | D3: No mandatory time limit on anticipatory bail
A4: Q5 | B4: Ritu Chhabaria (2023) | C4: Kapil Wadhawan, 2024 INSC 58; Shaurya Sunil Kumar Singh, 2026 INSC 666 | D4: A timely charge-sheet defeats default bail; deferral order of May 2023; review dismissed Aug 2025
A5: Q7 | B5: Damodar S. Prabhu (2010) 5 SCC 663 | C5: Sanjabij Tari, 2025 INSC 1158 | D5: Compounding costs cut to 0/5/7.5/10%
A6: Q9 | B6: Dashrath Rupsingh Rathod (2014) 9 SCC 129 | C6: NI (Amendment) Act 2015; Bridgestone (2016) 2 SCC 75 | D6: Payee's branch court has jurisdiction
A7: Q10 | B7: Mohan Lal (2018) 17 SCC 627 | C7: Mukesh Singh (2020) 10 SCC 120 | D7: No automatic acquittal when informant = investigator
A8: Q11 | B8: Kanhaiyalal (2008) 4 SCC 668 | C8: Tofan Singh (2021) 4 SCC 1 | D8: s.67 NDPS statements inadmissible as confessions
A9: Q15 | B9: Rajesh Sharma (2017) 10 SCC 472 | C9: Social Action Forum (2018) 10 SCC 443 → Shivangi Bansal, 2025 INSC 883 | D9: FWC removed in 2018, restored via the Allahabad HC guidelines in 2025; conflict with the larger bench unresolved
A10: Q18 | B10: Bombay HC, Satish (2021) | C10: AG v. Satish, 2021 INSC 762 | D10: Skin-to-skin test rejected; sexual intent governs
A11: Q21 | B11: Shafhi Mohammad (2018) 2 SCC 801 | C11: Arjun Panditrao Khotkar (2020) 7 SCC 1 | D11: 65B / BSA 63 certificate mandatory
A12: Q24 | B12: Vijay Madanlal Choudhary (2022), read alone | C12: Tarsem Lal, 2024 INSC 434; Pankaj Bansal, 2023 INSC 866 | D12: No ED arrest after cognizance; review of Vijay Madanlal pending
... A14: Q27 | B14: Sangeet v. State of Haryana (2013) 2 SCC 452 | C14: In Re Policy Strategy, 2025 INSC 239 | D14: State must consider eligible convicts without an application

Sheet To Verify
A1: # | B1: Answers needing verification by a practising advocate
A2: 1 | B2: Q15 (498A/BNS 85): Shivangi Bansal (two judges, 2025) endorses Family Welfare Committees that Social Action Forum (three judges, 2018) had disapproved. Check how trial courts and police are actually applying it, and whether any later bench has clarified it.
A3: 2 | B3: Q5 (default bail): Confirm what happened to the Union's 2023 recall application in Ritu Chhabaria and the related ED v. Manpreet Singh Talwar matter, beyond the CBI review dismissed in Aug 2025.
A4: 3 | B4: Q1 (written grounds): Whether Mihir Rajesh Shah applies prospectively. A Delhi HC Division Bench in Karan Singh v. State (NCT of Delhi), 2026:DHC:570-DB, held it prospective, but a later Delhi HC NDPS ruling rejected that view; check the Supreme Court's own position.
A5: 4 | B5: Q24 (PMLA): The Vijay Madanlal review is pending before a bench reconstituted on 20 Aug 2026 and could change the bail framework.
A6: 5 | B6: Q20 (BNS 69): How courts separate BNS 69 from BNS 64 (rape) for post-July 2024 conduct.
A7: 6 | B7: Q30 (BNS 316(2)): AZB & Partners' BNS overview confirms criminal breach of trust "is now punishable with imprisonment which may extend to a term of five years instead of three years under IPC"; this is still secondary, so confirm against the India Code text.
A8: 7 | B8: Citations confirmed only secondhand: the SCC cite for AG v. Satish (only 2021 SCC OnLine SC 980 / AIR 2022 SC 13 confirmed); neutral cites for Bridgestone, Social Action Forum and the Mahajan review (none found); the 2019 INSC 939 and 2018 INSC 714 cites (Casemine only). Citations given from standard reports without a retrieved URL (D.K. Basu, Arnesh Kumar, Salauddin, Dashrath, Kanhaiyalal, Bhajan Lal, Indian Oil v. NEPC, Rajesh Sharma, Bachan Singh, Shafhi Mohammad, Mahajan, Sangeet, Bhagwan Rama Shinde Gosai, Pulicherla Nagaraju, Amardeep Singh) should be checked on indiankanoon.org before the set is locked.

Sheet Sources
A1: # | B1: Publisher | C1: Title | D1: URL
A2: 1 | B2: indiaproai | C2: IPC Section 420 / BNS Section 318 — Cheating & Dishonestly Inducing Delivery of Property | D2: https://indiaproai.com/legal-guides/ipc-section-420-bns-318-cheating-complete-guide-india
A3: 2 | B3: verdictum | C3: Supreme Court: Informing Grounds Of Arrest Mandatory For All Offences; Must Be Communicated In Writing Atleast 2 Hrs Prior To Production Of Arrestee Before Magistrate | D3: https://www.verdictum.in/court-updates/supreme-court/mihir-rajesh-shah-v-state-of-maharashtra-2025-insc-1288-grounds-of-arrest-1597198
A4: 3 | B4: livelaw | C4: Supreme Court's 'Mihir Rajesh Shah' Ruling On Written Grounds Of Arrest Operates Prospectively: Delhi High Court | D4: https://www.livelaw.in/high-court/delhi-high-court/delhi-high-court-supreme-court-mihir-rajesh-shah-ruling-written-grounds-arrest-prospectively-520838
A5: 4 | B5: scobserver | C5: 2025 INSC 1288 Criminal Appeal No. 2195 of 2025 Page 1 of 52 REPORTABLE | D5: https://www.scobserver.in/wp-content/uploads/2025/11/SCOLR-Judgement_Mihir-Rajesh-Shah-v-State-of-Maharashtra.pdf
A6: 5 | B6: indiankanoon | C6: Mihir Rajesh Shah vs The State Of Maharashtra on 6 November, 2025 | D6: https://indiankanoon.org/doc/75521991/
A7: 6 | B7: Substack | C7: Bolstering Personal Liberty: The Supreme Court’s Reaffirmation of the Citizen’s Right to Know the Grounds of Arrest | D7: https://kbssidhu.substack.com/p/bolstering-personal-liberty-the-supreme
A8: 7 | B8: verdictum | C8: Electronic Communication Not Valid Mode Of Service Of Notice U/S. 35 Of BNSS: Supreme Court Upholds Order Barring WhatsApp Notice | D8: https://www.verdictum.in/court-updates/supreme-court/satender-kumar-antil-v-central-bureau-of-investigation-2025-insc-909-electronic-communication-service-of-notice-section-35-bnss-whatsapp-1586826
A9: 8 | B9: mhcolaw | C9: criminal law update: legal notices via whatsapp not ... | D9: https://www.mhcolaw.com/updates/criminal-law-update-legal-notices-via-whatsapp-not-permissible-rules-supreme-court/172
A10: 9 | B10: livelaw | C10: Supreme Court Quarterly Digest 2026 - Bharatiya Nagarik Suraksha Sanhita (BNSS) | D10: https://www.livelaw.in/supreme-court/supreme-court-judgments-and-orders-quarterly-digest-bnss-2026-532575
A11: 10 | B11: collegedunia | C11: in which case it was held by the supreme court tha 66b06e9ca5e223d061ecb50f | D11: https://questions.collegedunia.com/exams/questions/in-which-case-it-was-held-by-the-supreme-court-tha-66b06e9ca5e223d061ecb50f
A12: 11 | B12: casemine | C12: Reaffirming the Broad Scope of Anticipatory Bail under Section 438 CrPC: Sushila Aggarwal v. State (2020 INSC 106): Supreme Court Of India | D12: https://www.casemine.com/commentary/in/reaffirming-the-broad-scope-of-anticipatory-bail-under-section-438-crpc:-sushila-aggarwal-v.-state-(2020-insc-106)/view
A13: 12 | B13: scconline | C13: Whether chargesheet filed without FSL report entitle accused to default bail? SC refers to larger bench | D13: https://www.scconline.com/blog/post/2024/04/15/chargesheet-without-fsl-report-accused-default-bail-sc-refers-larger-bench-legal-news/
... A121: 120 | B121: livelaw | C121: Bharatiya Nagarik Suraksha Sanhita (BNSS) And Bhartiya Nyaya Sanhita (BNS) Half-Yearly Digest: January - June, 2026 | D121: https://www.livelaw.in/top-stories/bnss-bns-latest-judgments-half-yearly-digest-2026-542012
